[
  {
    "saami saami": [
      {
        "url": "https://share.mxtakatak.com/vc3YeB1o-PAM",
        "user": " Mona Singh Official  ",
        "desc": "Saami saami \ud83d\udd25 #dance #mxtakatakcreatorsclub #takataktrending #monasingh @MX_TakaTak_Official  24/1/22",
        "likes": "50.3K",
        "shares": "226",
        "comments": "179"
      },
      {
        "url": "https://share.mxtakatak.com/OiWymIU6-j5k",
        "user": " Veerangnajd  ",
        "desc": "Saami Saami #saamisaami #pushpa #takatakcreator #takataktrending #mxtakatak @MX_TakaTak_Official #veerangna",
        "likes": "36.4K",
        "shares": "192",
        "comments": "70"
      },
      {
        "url": "https://share.mxtakatak.com/mZW3zEie-66k",
        "user": " Mukesh Jaiswal  ",
        "desc": "Saami saami \u2764\ufe0f #mxtakatak",
        "likes": "104.8K",
        "shares": "263",
        "comments": "168"
      },
      {
        "url": "https://share.mxtakatak.com/ofQyymoc-alB",
        "user": " Reshmi jaiswal  ",
        "desc": "Saami\u2764\ufe0f@mxtaktakindia #takataktrending #takatakcreator #mxtatakatak",
        "likes": "18.8K",
        "shares": "93",
        "comments": "71"
      },
      {
        "url": "https://share.mxtakatak.com/bg9pBBH2-1TE",
        "user": " Anuj_Tutter00  ",
        "desc": "Saami Saami viral dance \ud83d\udd25 #pushpa #pushparaj #saamisaami @MX_TakaTak_Official ",
        "likes": "13.4K",
        "shares": "96",
        "comments": "43"
      },
      {
        "url": "https://share.mxtakatak.com/JJrBnPmj-VNm",
        "user": " Littele Dancer Hr Crew  ",
        "desc": "#saamisaami @MX_TakaTak_Official  sami sami 14/01/22",
        "likes": "83.5K",
        "shares": "208",
        "comments": "45"
      },
      {
        "url": "https://share.mxtakatak.com/LMkEjirj-jyo",
        "user": " Anuj_Tutter00  ",
        "desc": "Saami Saami #saamisaami #pushpa #fingerking #tutter00 #takatakcreator @MX_TakaTak_Official ",
        "likes": "31.1K",
        "shares": "145",
        "comments": "49"
      },
      {
        "url": "https://share.mxtakatak.com/bB5t9zpy-h2m",
        "user": " Aashishrajput7313  ",
        "desc": "Saami Saami \ud83d\udd25\ud83d\udd25#saamisaami #aashishrajput7313  @MX_TakaTak_Official ",
        "likes": "30.5K",
        "shares": "100",
        "comments": "22"
      },
      {
        "url": "https://share.mxtakatak.com/om4AiVjz-Mow",
        "user": " Afsuu  ",
        "desc": "Saami\ud83d\udd25\ud83d\ude0e#mxtakatak #pushpa #explore #takatakcreator #explorepage #afsuu #dance #saami",
        "likes": "113.1K",
        "shares": "109",
        "comments": "154"
      },
      {
        "url": "https://share.mxtakatak.com/mzPeWqFP-Yv6",
        "user": " Abarna Sundarraman  ",
        "desc": "Saamay #saami #saamy #tamil #abarnasundarraman #song",
        "likes": "8233",
        "shares": "27",
        "comments": "17"
      },
      {
        "url": "https://share.mxtakatak.com/g76u6TO7-4iz",
        "user": " Divyanka Sirohi  ",
        "desc": "Saame \u26a1\ufe0f #saamisaami #saami",
        "likes": "11.1K",
        "shares": "37",
        "comments": "56"
      },
      {
        "url": "https://share.mxtakatak.com/0Ado4kYB-e6x",
        "user": " Rashi singh  ",
        "desc": "Na saami #mxtakatak #takataktrending #takatakcreator",
        "likes": "6466",
        "shares": "27",
        "comments": "16"
      },
      {
        "url": "https://share.mxtakatak.com/tz8srXBN-N89",
        "user": " Paper queen  ",
        "desc": "saami saami #mxtakatak #viraltrend #takatakcreator #takataktrending #saamisaami ",
        "likes": "8692",
        "shares": "34",
        "comments": "20"
      },
      {
        "url": "https://share.mxtakatak.com/31Ww735E-Oyz",
        "user": " Mona Singh Official  ",
        "desc": "Saami saami #pushpa @MX_TakaTak_Official  3/1/22",
        "likes": "64.9K",
        "shares": "221",
        "comments": "149"
      },
      {
        "url": "https://share.mxtakatak.com/KPzBxR4O-WwX",
        "user": " Swetha Subramanian  ",
        "desc": "Pushpa Saami Fail\ud83d\ude02 #saami #saamisaami #pushpa #alluarjun #mxtakatak  #mxtakatakcreator #trending #dancefail ",
        "likes": "11.7K",
        "shares": "44",
        "comments": "17"
      },
      {
        "url": "https://share.mxtakatak.com/7sv18G27-PHA",
        "user": " Puja Roy  ",
        "desc": "Red saami  #saamisaami @MX_TakaTak_Official  10/1/22",
        "likes": "30.0K",
        "shares": "124",
        "comments": "98"
      },
      {
        "url": "https://share.mxtakatak.com/zE6cLqG1-EX0",
        "user": " Nancy Jennifer  ",
        "desc": "saamy #Saami #saamisaami #pushpa #mxtakatakcreator #nancyjennifer #mxtakatak #takatakcreator ",
        "likes": "6855",
        "shares": "19",
        "comments": "24"
      },
      {
        "url": "https://share.mxtakatak.com/uw4cy4dq-3SM",
        "user": " Veerangnajd  ",
        "desc": "Saami Saami #saamisaami #jdveera #veerangna #mxtakatak #takatakcreator #mxtakataktrending @MX_TakaTak_Official",
        "likes": "38.8K",
        "shares": "189",
        "comments": "94"
      },
      {
        "url": "https://share.mxtakatak.com/gs0PuPea-uhd",
        "user": " cuty_beauty_khan",
        "desc": "Saami saami \ud83d\udd25\ud83d\udd25..#bkfam #saamisaami #beautykhan ",
        "likes": "105",
        "shares": "27",
        "comments": "2"
      },
      {
        "url": "https://share.mxtakatak.com/qC43G4xu-CRV",
        "user": " divyashree  ",
        "desc": "#saamisaami #pushpa #trending #viral",
        "likes": "103.5K",
        "shares": "455",
        "comments": "261"
      }
    ]
  },
  {
    "dholida": [
      {
        "url": "https://share.mxtakatak.com/gL4Jc0LC-tk8",
        "user": " @_Yunush____",
        "desc": "dholida \ud83d\udc99 #love #song #dholida Ab khush sis \ud83d\ude43",
        "likes": "937",
        "shares": "528",
        "comments": "6"
      },
      {
        "url": "https://share.mxtakatak.com/7bkoupze-fdx",
        "user": " Bhavi_Mewada\ud83e\udd8b  ",
        "desc": "Dholida\ud83d\udd25\ud83d\ude0d #mxcreator #navratri #dholida #trending #bhavicrew #takataktrending #takatakcreator",
        "likes": "2293",
        "shares": "23",
        "comments": "4"
      },
      {
        "url": "https://share.mxtakatak.com/4AslEAnW-IxV",
        "user": " Tejas & Ishpreet  ",
        "desc": "Dholida With Ishpreet Dang #dholida #dance #dancefitlive #Tejish #2020 ",
        "likes": "78.1K",
        "shares": "73",
        "comments": "215"
      },
      {
        "url": "https://share.mxtakatak.com/9yb8lhpj-Wcf",
        "user": " Herbestmoves  ",
        "desc": "DHOLIDAA\ud83d\udd25 #dholida #navratri #garba",
        "likes": "22.4K",
        "shares": "39",
        "comments": "12"
      },
      {
        "url": "https://share.mxtakatak.com/1mBPlGdL-zKH",
        "user": " Aaisha Jain",
        "desc": "#navratri #mxtakatakcreatorsclub #dholida #garba #dance",
        "likes": "383",
        "shares": "9",
        "comments": "Comment"
      },
      {
        "url": "https://share.mxtakatak.com/viKEZBxl-oBa",
        "user": " muigon3113",
        "desc": "The wolf climbed over the wall and was scratched by the barbed wire\ud83d\udc3a\ud83d\udc3a\ud83d\udc3a\ud83d\ude16\ud83d\ude16\ud83d\ude16#wolf #HolidaysOurWay #tabletop ",
        "likes": "643",
        "shares": "12",
        "comments": "20"
      },
      {
        "url": "https://share.mxtakatak.com/Mj1ob7ha-3o9",
        "user": " Awesome Cars",
        "desc": "\u2764\ufe0f #RnBVibes #fty #\ud83d\ude97 ",
        "likes": "6920",
        "shares": "35",
        "comments": "45"
      },
      {
        "url": "https://share.mxtakatak.com/EdU27Nc8-e92",
        "user": " Awesome Cars",
        "desc": "\ud83e\udd2b\ud83e\udd2b\ud83e\udd2b #RnBVibes #fty #\ud83d\ude97 ",
        "likes": "14.8K",
        "shares": "66",
        "comments": "138"
      },
      {
        "url": "https://share.mxtakatak.com/SKq7SXvd-0Bg",
        "user": " Awesome Cars",
        "desc": "\ud83d\udeb4\ud83d\udeb4\ud83d\udeb4 #RnBVibes #fty #\ud83d\udeb4 ",
        "likes": "1588",
        "shares": "85",
        "comments": "11"
      },
      {
        "url": "https://share.mxtakatak.com/ZfpdakYF-oyd",
        "user": " Foodtext",
        "desc": "#pancake #holidayszn #fyp",
        "likes": "49.3K",
        "shares": "694",
        "comments": "438"
      },
      {
        "url": "https://share.mxtakatak.com/p9ulXFHC-5px",
        "user": " Daily DIYs",
        "desc": "#fyp #foryoupage #foryou ",
        "likes": "11.6K",
        "shares": "285",
        "comments": "100"
      },
      {
        "url": "https://share.mxtakatak.com/Zo3ab67e-fpt",
        "user": " Jill Harrison656",
        "desc": "#loveyl #adorable #funny ",
        "likes": "750",
        "shares": "18",
        "comments": "22"
      },
      {
        "url": "https://share.mxtakatak.com/Zpomes68-BLJ",
        "user": " How to Paint",
        "desc": "#holidaycrafts \u2764\ufe0f",
        "likes": "42",
        "shares": "2",
        "comments": "Comment"
      },
      {
        "url": "https://share.mxtakatak.com/8WfgUnr4-sEv",
        "user": " Anjali dalal  ",
        "desc": "#dhol #takatakcreator #mxtakatak #anjalidalal",
        "likes": "3317",
        "shares": "9",
        "comments": "17"
      },
      {
        "url": "https://share.mxtakatak.com/jY7qWjmt-g2u",
        "user": " Awesome Cars",
        "desc": "\ud83e\udd23\ud83d\ude31 #fty #\ud83d\ude97 #carslover ",
        "likes": "1876",
        "shares": "9",
        "comments": "5"
      },
      {
        "url": "https://share.mxtakatak.com/0HjqYced-taG",
        "user": " Ojasvi Verma  ",
        "desc": "Dholida \ud83d\ude02\u2728 #mxtakatakcreator #mxtakataktrending #comedyvideo ",
        "likes": "37.7K",
        "shares": "84",
        "comments": "55"
      },
      {
        "url": "https://share.mxtakatak.com/BSQ35g3L-dBx",
        "user": " Ruke",
        "desc": "#RnBVibes #foryou #fyp",
        "likes": "49.0K",
        "shares": "1400",
        "comments": "411"
      },
      {
        "url": "https://share.mxtakatak.com/xRlfsqzg-Rpv",
        "user": " Create Room",
        "desc": "Attention all moms! This is for you \ud83e\udd70 #fyp #holidaycrafts",
        "likes": "597",
        "shares": "26",
        "comments": "11"
      },
      {
        "url": "https://share.mxtakatak.com/7ixz4ig1-aR4",
        "user": " Adventural Diaries",
        "desc": "Dholida \ud83d\ude02\u2728 #mxtakatakcreator #mxtakataktrending #comedyvideo ",
        "likes": "3101",
        "shares": "112",
        "comments": "31"
      },
      {
        "url": "https://share.mxtakatak.com/Ru1rpBG5-wi4",
        "user": " Suman Modi  ",
        "desc": "Dhol Thali Dance \ud83d\udc9b #rajasthanifolk #rajasthani #dholthalidance #sumanmodi #mxtakatakcreatorsclub #trending #dholbeat",
        "likes": "9006",
        "shares": "37",
        "comments": "29"
      }
    ]
  },
  {
    "oo antava": [
      {
        "url": "https://share.mxtakatak.com/0o9jToh0-zBc",
        "user": " Starleth3re_",
        "desc": "Oo antava oo oo antava #samantharuthprabhu #samanthahot ...#samanthaakkineni ",
        "likes": "435",
        "shares": "41",
        "comments": "5"
      },
      {
        "url": "https://share.mxtakatak.com/XMA60l1I-7VX",
        "user": " t135244057",
        "desc": "Oo Antava Oo Oo Antava \ud83d\ude06#ooantavaooooantava",
        "likes": "417",
        "shares": "26",
        "comments": "2"
      },
      {
        "url": "https://share.mxtakatak.com/yuXvxXjP-qvD",
        "user": " Shruti Poojary  ",
        "desc": "Oo Antava in our style\ud83e\udd2a #pushpa #ooantava #ooantavaooooantava #takatakcreator #mxtakatak #mxtakatakcreatorsclub #funnyvideos",
        "likes": "20.2K",
        "shares": "166",
        "comments": "23"
      },
      {
        "url": "https://share.mxtakatak.com/emxlovvk-6y2",
        "user": " imran  ",
        "desc": "#pushpa #ooantava #mxtakatakcreator #takatakcreator #takataktrending",
        "likes": "8833",
        "shares": "56",
        "comments": "9"
      },
      {
        "url": "https://share.mxtakatak.com/2dwplufe-8Nh",
        "user": " Aashishrajput7313  ",
        "desc": "Oo antava  trending #pushpa #takataktrending #aashishrajput7313 #dance @MX_TakaTak_Official  #Oantava",
        "likes": "47.1K",
        "shares": "242",
        "comments": "83"
      },
      {
        "url": "https://share.mxtakatak.com/S5XcmUfv-D3r",
        "user": " Afsuu  ",
        "desc": "Oo antava\ud83d\udd25#mxtakatak #explorepage #explore #takatakcreator #afsuu #foryou #pushpa #song #OAntava",
        "likes": "38.8K",
        "shares": "93",
        "comments": "44"
      },
      {
        "url": "https://share.mxtakatak.com/29eAAas3-xud",
        "user": " Afsuu  ",
        "desc": "Oo Antava\u2764\ufe0f\u200d\ud83d\udd25#explorepage #explore #dance #song #takatakcreator #mxtakatak #foryoupage",
        "likes": "13.2K",
        "shares": "23",
        "comments": "2"
      },
      {
        "url": "https://share.mxtakatak.com/kymvgaex-rWu",
        "user": " Keshavi Chhetri \ud83d\udc51  ",
        "desc": "Oo antava remix #pushpa #oantava #telugu",
        "likes": "11.4K",
        "shares": "51",
        "comments": "5"
      },
      {
        "url": "https://share.mxtakatak.com/8pduFA5R-Hhm",
        "user": " Seep Grover  ",
        "desc": "Oo Antava Maava\u2764\ufe0f #pushpa #mxtakatakcreatorsclub #takataktrending #takatakcreator #viral #seepgrover #Oantava",
        "likes": "42.6K",
        "shares": "202",
        "comments": "307"
      },
      {
        "url": "https://share.mxtakatak.com/4x0LytHw-a2t",
        "user": " Parul Arora",
        "desc": "Oo antava \ud83d\udd25#saree #sareelove #sareefashion ",
        "likes": "53",
        "shares": "4",
        "comments": "1"
      },
      {
        "url": "https://share.mxtakatak.com/01ctZ06O-bpj",
        "user": " TellyTalkIndia  ",
        "desc": "@rakhisawant2511 performs Samantha Ruth Prabhu's Oo Antava with Ritesh. \ud83d\ude0d\u2764\ud83d\udd25#tellytalkindia #rakhisawant #ritiesh #ooantava #samatharuthprabhu ",
        "likes": "684",
        "shares": "6",
        "comments": "2"
      },
      {
        "url": "https://share.mxtakatak.com/kJn8spak-6oh",
        "user": " Mona Singh Official  ",
        "desc": "Oo Antava \ud83d\udd25 #pushpa @MX_TakaTak_Official  1/1/22 #OAntava",
        "likes": "62.9K",
        "shares": "233",
        "comments": "240"
      },
      {
        "url": "https://share.mxtakatak.com/d2amNiBW-3Op",
        "user": " Viral Tolly",
        "desc": "#samantharuthprabhu slow motion\ud83e\udd29#ooantavaooooantava #samantha ",
        "likes": "473",
        "shares": "57",
        "comments": "5"
      },
      {
        "url": "https://share.mxtakatak.com/J8lAAdK2-fJW",
        "user": " Anuj_Tutter00  ",
        "desc": "Oo Antava #pushpa #Pushpa #ooantava #tutter00 #fingerking  @MX_TakaTak_Official ",
        "likes": "27.1K",
        "shares": "138",
        "comments": "26"
      },
      {
        "url": "https://share.mxtakatak.com/WB3rE4r3-cGw",
        "user": " Tanvee Gadekar  ",
        "desc": "Oo antava ma oo antava #pushpa #ooantavaooooantava #mxtakatak #takataktrending",
        "likes": "8696",
        "shares": "60",
        "comments": "28"
      },
      {
        "url": "https://share.mxtakatak.com/R7hihocP-CHC",
        "user": " Tithi Basu  ",
        "desc": "#antavama ",
        "likes": "7990",
        "shares": "18",
        "comments": "44"
      },
      {
        "url": "https://share.mxtakatak.com/cnghLcIi-KID",
        "user": " \u2022BinduGowda\ud83d\udc99\u2022",
        "desc": "Oo antava mava \ud83d\udd25 #bindugowda #pushpa #ooantavaooooantava ",
        "likes": "631",
        "shares": "61",
        "comments": "36"
      },
      {
        "url": "https://share.mxtakatak.com/xyAJH0sf-itK",
        "user": " Karnataka trends",
        "desc": "Oo antava Mava #ooantaavamawa",
        "likes": "139",
        "shares": "24",
        "comments": "6"
      },
      {
        "url": "https://share.mxtakatak.com/z7qetXmS-rtw",
        "user": " Nancy Jennifer  ",
        "desc": "oo antava mama #pushpa #ooantava #oobolega #oosolriyamama #mxtakatakcreator #mxtakatak #nancyjennifer ",
        "likes": "6178",
        "shares": "11",
        "comments": "7"
      },
      {
        "url": "https://share.mxtakatak.com/JFIhpqIl-y9y",
        "user": " Maari  ",
        "desc": "Oo antava oo oo antava #maari #tamil #dhanush #mxtakatak #takatakcreator",
        "likes": "1765",
        "shares": "9",
        "comments": "8"
      }
    ]
  },
  {
    "srivalli": [
      {
        "url": "https://share.mxtakatak.com/7K7oQAfu-9av",
        "user": " user6283136832854",
        "desc": "Teri jhalak asharfi #srivalli #pushpa",
        "likes": "10.4K",
        "shares": "5167",
        "comments": "160"
      },
      {
        "url": "https://share.mxtakatak.com/lUSlB2Qq-CH6",
        "user": " Chetan Monga  ",
        "desc": "Mai Jhukega Nahi mummy\ud83d\ude0f\ud83d\ude02 #srivalli",
        "likes": "34.2K",
        "shares": "247",
        "comments": "79"
      },
      {
        "url": "https://share.mxtakatak.com/kCwA2y7x-E0f",
        "user": " Irfan Sayed  ",
        "desc": "Pushpa #srivalli @emmi_10 @MX_TakaTak_Official",
        "likes": "22.4K",
        "shares": "84",
        "comments": "75"
      },
      {
        "url": "https://share.mxtakatak.com/843i6O3x-taw",
        "user": " Moni kundu  ",
        "desc": "#srivalli #takataktrending #chintuandmom #takatakcreator",
        "likes": "16.2K",
        "shares": "75",
        "comments": "36"
      },
      {
        "url": "https://share.mxtakatak.com/7hvz85jz-z56",
        "user": " \u2b50Anshu Jha Rockstar\u2b50  ",
        "desc": "#srivalli #pushpa #takataktrending #takatakcreator #anshujharockstar \ud83d\ude0a\ud83d\ude0a",
        "likes": "32.6K",
        "shares": "270",
        "comments": "3138"
      },
      {
        "url": "https://share.mxtakatak.com/mh1nmoTo-WKa",
        "user": " Veerangnajd  ",
        "desc": "Srivalli #srivalli #mxtakatak #takatakcreator #takataktrending #jdveera #veerangna @MX_TakaTak_Official",
        "likes": "9262",
        "shares": "30",
        "comments": "19"
      },
      {
        "url": "https://share.mxtakatak.com/0YZ8ddGB-5gn",
        "user": " Nira Jain  ",
        "desc": "Srivalli #srivalli #takatakcreator #takataktrending #foryou #foryoupage #nirajain",
        "likes": "10.3K",
        "shares": "33",
        "comments": "26"
      },
      {
        "url": "https://share.mxtakatak.com/z5nzA0JA-jbb",
        "user": " Kajal Chandravanshi  ",
        "desc": "#srivalli #pushpa #love #kajal_c_v_s_360 #takatakcreatorclub",
        "likes": "42.3K",
        "shares": "200",
        "comments": "145"
      },
      {
        "url": "https://share.mxtakatak.com/mUznjJ5F-pBf",
        "user": " Rohit Singhania  ",
        "desc": "My Mom \ud83d\ude0d #srivalli",
        "likes": "14.4K",
        "shares": "46",
        "comments": "38"
      },
      {
        "url": "https://share.mxtakatak.com/eBpXHm8w-Ek6",
        "user": " MR CHARLIE 07  ",
        "desc": "#srivalli \ud83d\ude0d\ud83d\ude48",
        "likes": "8236",
        "shares": "23",
        "comments": "2"
      },
      {
        "url": "https://share.mxtakatak.com/u2lBjVcC-kzt",
        "user": " Ravinderbhai Singh  ",
        "desc": "#pushpa #srivalli ",
        "likes": "3338",
        "shares": "94",
        "comments": "9"
      },
      {
        "url": "https://share.mxtakatak.com/CRe0dc43-Bsu",
        "user": " vivek rokz  ",
        "desc": "#srivalli #pushpa #takataktrending #takatakcreator",
        "likes": "3626",
        "shares": "5",
        "comments": "6"
      },
      {
        "url": "https://share.mxtakatak.com/5m3OznVP-iGa",
        "user": " Mukesh Jaiswal  ",
        "desc": "Tu meri srivalli \ud83d\ude02 #srivalli #mxtakatak #takatakcreator",
        "likes": "38.5K",
        "shares": "130",
        "comments": "46"
      },
      {
        "url": "https://share.mxtakatak.com/5h271nRr-g01",
        "user": " Honey Richard  ",
        "desc": "\ud83d\ude02\ud83d\ude02 #srivalli #comedy #funny @MX_TakaTak_Official",
        "likes": "5328",
        "shares": "112",
        "comments": "17"
      },
      {
        "url": "https://share.mxtakatak.com/eRkstzm7-3T1",
        "user": " MUSKAN SHARMA",
        "desc": "#srivalli",
        "likes": "82",
        "shares": "10",
        "comments": "2"
      },
      {
        "url": "https://share.mxtakatak.com/A2aOw4Ri-ysx",
        "user": " Hanif Hasmani  ",
        "desc": "#Srivalli",
        "likes": "11.2K",
        "shares": "76",
        "comments": "31"
      },
      {
        "url": "https://share.mxtakatak.com/8MlxmnTB-8rl",
        "user": " Lavina Rohra  ",
        "desc": "#pushpa #srivalli #lavdance",
        "likes": "5971",
        "shares": "57",
        "comments": "13"
      },
      {
        "url": "https://share.mxtakatak.com/857roj6H-b6r",
        "user": " sradha panigrahi  ",
        "desc": "Srivalli \ud83e\udd70 #sradhapanigrahi #takatakcreator #takataktrending #srivalli #pushpa #hindisong",
        "likes": "11.7K",
        "shares": "28",
        "comments": "61"
      },
      {
        "url": "https://share.mxtakatak.com/gCsAj9Es-0nv",
        "user": " SUPERSTARDEWASI 99",
        "desc": "Srivalli \ud83d\udd25\ud83c\udfb5 #taklubaadshah #srivalli",
        "likes": "44",
        "shares": "9",
        "comments": "Comment"
      },
      {
        "url": "https://share.mxtakatak.com/kcWMPldV-YAT",
        "user": " Sanchi Rai  ",
        "desc": "#srivalli #takatak #takatakcreator #mxtakatak #takataktrending ",
        "likes": "46.8K",
        "shares": "218",
        "comments": "278"
      }
    ]
  },
  {
    "sare bolo bewafa": [
      {
        "url": "https://share.mxtakatak.com/rih9aBUl-27S",
        "user": " \uff20Jagdish03",
        "desc": "Bewafa Hai Tu #satets #share #plz_support_follow_and_like Share",
        "likes": "1554",
        "shares": "1561",
        "comments": "23"
      },
      {
        "url": "https://share.mxtakatak.com/qppn00df-NtE",
        "user": " ajay777",
        "desc": "\u0915\u094b\u0908 \u0907\u0938\u0915\u0940 \u0936\u093e\u0926\u0940 \u0915\u0930\u093e\u0913\ud83e\udd23@sofia_ansari9__ @_.zara._ @angelrai07 @zaralovers #mxstudio #takatakcreator #takataktrending #bollywood #sad_lov\u0435_status #bewafa ",
        "likes": "144.9K",
        "shares": "2827",
        "comments": "1549"
      },
      {
        "url": "https://share.mxtakatak.com/A1BtIi5b-VpK",
        "user": " Vicky John  ",
        "desc": "#mujhko_ye_teri_bewafai_mar_dalegi #SwagStepChallenge #bollywood",
        "likes": "9728",
        "shares": "735",
        "comments": "10"
      },
      {
        "url": "https://share.mxtakatak.com/1ACgxSwO-Nzj",
        "user": " Sinnu Singh Rajput",
        "desc": "bewafa \ud83d\udc9a\ud83d\udc9abewafa hai tu\ud83d\udc95\ud83d\udc95 Sinnu \ud83c\udf3a Singh \u2764\ufe0f Rajput \ud83d\udc95\ud83d\udc95\ud83d\udc4c\ud83c\udf39",
        "likes": "1581",
        "shares": "695",
        "comments": "15"
      },
      {
        "url": "https://share.mxtakatak.com/o8AvlyAb-zpO",
        "user": " Shoaib Akhta334",
        "desc": "#bewafai #sad",
        "likes": "652",
        "shares": "539",
        "comments": "3"
      },
      {
        "url": "https://share.mxtakatak.com/4rqji6c2-yw1",
        "user": " Rohit Singhania  ",
        "desc": "Har ladki jo shaadi na kare wo bewafa nhi hooti \ud83d\ude4f uske maa baap \ud83d\ude42 Insta - Rohit1209_",
        "likes": "13.9K",
        "shares": "391",
        "comments": "25"
      },
      {
        "url": "https://share.mxtakatak.com/97oiby4U-4u8",
        "user": " Mr. Alam\ud83c\uddee\ud83c\uddf3  ",
        "desc": "AANA PAREGA...\ud83d\ude02\ud83e\udd2d\u2764\ufe0f #trending #viral #takataktrending #bewafatera ",
        "likes": "67.7K",
        "shares": "248",
        "comments": "4048"
      },
      {
        "url": "https://share.mxtakatak.com/66kZ96UK-2A5",
        "user": " Paayaliah  ",
        "desc": "\ud83d\udd25Bewafa #saree #trend #fyp",
        "likes": "5880",
        "shares": "48",
        "comments": "75"
      },
      {
        "url": "https://share.mxtakatak.com/t2oM2iKv-q0d",
        "user": " thiscouple  ",
        "desc": "sare ek bari waheguru ji bolo sade char sahibzadeyan ne sadi rksha leyi qurbani ditiyan #thiscouple",
        "likes": "22.9K",
        "shares": "2354",
        "comments": "96"
      },
      {
        "url": "https://share.mxtakatak.com/5Vm66Z5p-kH6",
        "user": " Amit Raj3483",
        "desc": "Naa Kare Bewafai Koi Dil Se Kabhi",
        "likes": "606",
        "shares": "641",
        "comments": "2"
      },
      {
        "url": "https://share.mxtakatak.com/finzKE87-WxE",
        "user": " \ud83d\udc51bykhanmoni\ud83d\udc51  ",
        "desc": "sala \ud83d\ude20\ud83d\ude20\ud83d\ude20 gold digger girls ! i hate gold digger girls ! tum log kya bolte ?#love #facklove #bewafa",
        "likes": "14.0K",
        "shares": "461",
        "comments": "14"
      },
      {
        "url": "https://share.mxtakatak.com/dR016MZR-7tv",
        "user": " \ud83d\udc94Sayar king \ud83d\udcaa",
        "desc": "Delhi ke sare bewafa ",
        "likes": "454",
        "shares": "132",
        "comments": "2"
      },
      {
        "url": "https://share.mxtakatak.com/wqxlws1J-fky",
        "user": " RizXtar.  ",
        "desc": "mujhe bewafai ka nahi gila... mujhe meri wafaao ka aise bhi kya sila mila \ud83d\udd25\u2764\ufe0f @sofia_ansari9__ #xtarmy #xtarmyforever #takatakmyhome #takataktrending",
        "likes": "395.4K",
        "shares": "337",
        "comments": "642"
      },
      {
        "url": "https://share.mxtakatak.com/vs3OXs1B-59z",
        "user": " RajeevPaswan ji",
        "desc": "#Rajeevpaswanji #Likeamusician #bewafai",
        "likes": "390",
        "shares": "488",
        "comments": "6"
      },
      {
        "url": "https://share.mxtakatak.com/C3c1vEy4-Kju",
        "user": " Varun Gupta 131",
        "desc": "bewafa tune mujhe pagal hi kar diya\ud83d\ude2d\ud83d\ude2d #foryou #love #viral ",
        "likes": "329",
        "shares": "331",
        "comments": "Comment"
      },
      {
        "url": "https://share.mxtakatak.com/nFqMycAh-u1A",
        "user": " J\u00dd\u00d3\u0164\u00cf \u015eH\u0158\u00c9\u00c9",
        "desc": "Hmse bewafa toy dur rahabe \u270b\ud83d\ude05 khortha Nagpuri hit \ud83d\udd25\ud83d\udd25.....#khorthasong #khorthareels #nagpurisong ",
        "likes": "201",
        "shares": "136",
        "comments": "4"
      },
      {
        "url": "https://share.mxtakatak.com/sMNrn8ts-x8d",
        "user": " Kaushar raj official",
        "desc": "Ajay Devgan ke bewafai video please video like aur follow kare love you Friends",
        "likes": "1400",
        "shares": "2743",
        "comments": "5"
      },
      {
        "url": "https://share.mxtakatak.com/u83zsnfv-mk5",
        "user": " Akash Chowdhary  ",
        "desc": "DIL \u2764\ufe0f\u2764\ufe0f LAGANE KO ABHI SARA JAHA BAKI HAI \ud83d\udd25 \ud83d\udd25\ud83d\udd25 \ud83d\udd25 #FlauntItYourWay #duet #shayar ",
        "likes": "14.0K",
        "shares": "506",
        "comments": "10"
      },
      {
        "url": "https://share.mxtakatak.com/fw26nEab-xsX",
        "user": " \ud83d\udc94Sayar king \ud83d\udcaa",
        "desc": "bewafae ki o sari hade ",
        "likes": "799",
        "shares": "634",
        "comments": "2"
      },
      {
        "url": "https://share.mxtakatak.com/z3gd90M8-FaF",
        "user": " Kaushar raj official",
        "desc": "bewafai video please video like aur follow kare love you Friends funny video",
        "likes": "1382",
        "shares": "2259",
        "comments": "8"
      }
    ]
  },
  {
    "maar khayegaa": [
      {
        "url": "https://share.mxtakatak.com/oXd2jC7T-2Mm",
        "user": " Mishti\ud83d\udd25  ",
        "desc": "maar khayegi ab \ud83d\ude20\ud83d\ude20\ud83d\ude02\ud83e\udd23#trend #trending #foryoupage ",
        "likes": "673.6K",
        "shares": "21.2K",
        "comments": "5691"
      },
      {
        "url": "https://share.mxtakatak.com/7uAMRQbE-u65",
        "user": " Angel Rai  ",
        "desc": "Ye aise hi mar khayega \ud83d\ude02\ud83d\ude02\ud83d\ude02#takatakcreator #trending #viral",
        "likes": "873.3K",
        "shares": "1346",
        "comments": "2222"
      },
      {
        "url": "https://share.mxtakatak.com/iw0Wsn5U-AiW",
        "user": " dynamic contents",
        "desc": "bhelpuri kaun khayega#insane #mxtakatak #mainbhisuperstar ",
        "likes": "44.3K",
        "shares": "603",
        "comments": "228"
      },
      {
        "url": "https://share.mxtakatak.com/P7LPkvPN-ljB",
        "user": " Maari  ",
        "desc": "Masal diya jayega beta #maari #rowdy #dhanush #mxtakatak #takatakcreator",
        "likes": "58.4K",
        "shares": "405",
        "comments": "89"
      },
      {
        "url": "https://share.mxtakatak.com/k1c2zfbd-BW3",
        "user": " Neetu Bisht  ",
        "desc": "Itni Maggie Kon Khayega \ud83d\ude39 #comedy #funny #trending",
        "likes": "54.9K",
        "shares": "186",
        "comments": "176"
      },
      {
        "url": "https://share.mxtakatak.com/2755frin-1PB",
        "user": " Sonal Dadhich  ",
        "desc": "Chhor Kar Kabhi Nahi Jayegaa\u2764\ufe0f\u2764\ufe0f #trending #love #takataktrending #featureme #MXTakaTak #shayari ",
        "likes": "166.2K",
        "shares": "1756",
        "comments": "5749"
      },
      {
        "url": "https://share.mxtakatak.com/4wYCK1Le-Zbj",
        "user": " Nita Shilimkar",
        "desc": "Kon khayega ye roti ? \ud83d\ude02 #nita #cutenessgirl #blooper",
        "likes": "60.3K",
        "shares": "1527",
        "comments": "1294"
      },
      {
        "url": "https://share.mxtakatak.com/uhIAXlkT-QLe",
        "user": " Gaurav Arora  ",
        "desc": "Dosa khayega koi \ud83d\ude0a #foodies",
        "likes": "326.4K",
        "shares": "98",
        "comments": "1074"
      },
      {
        "url": "https://share.mxtakatak.com/K8XWkZwf-jzg",
        "user": " Vinay.officiall786  ",
        "desc": "Tera Dil Bhi Jab Koi Dukhayega !!!!!!! #\ud83e\udd85 #officiall786 #wmk\ud83d\ude4f ",
        "likes": "25.7K",
        "shares": "747",
        "comments": "51"
      },
      {
        "url": "https://share.mxtakatak.com/mRtErLwg-2Vo",
        "user": " LIVE TIME 8:30 PM",
        "desc": "#comedy koi icecream khayega",
        "likes": "388",
        "shares": "33",
        "comments": "3"
      },
      {
        "url": "https://share.mxtakatak.com/C9bfd7tz-S5v",
        "user": " Arishfa Khan\ud83e\udd81",
        "desc": "Sehna aa jayega to fir rehna bhi aa jayega\u2764\ufe0f #arishfakhan #duetwitharishfa #arishfashayari ",
        "likes": "20.5K",
        "shares": "475",
        "comments": "71"
      },
      {
        "url": "https://share.mxtakatak.com/bYswtKw6-Jue",
        "user": " Colors TV  ",
        "desc": " #TicketToFinaleWeek paane ke iss aakhri mauke par kaun maar jaayega chauka?Dekhiye #BiggBoss15 tonight at 10:30 PM onl",
        "likes": "211",
        "shares": "4",
        "comments": "Comment"
      },
      {
        "url": "https://share.mxtakatak.com/tb9sLegT-5i3",
        "user": " Nikhil_Kumar_editor",
        "desc": "Tera Dil \u2764\ufe0fjab bhi koi dukhayega \ud83d\udc94\ud83d\udc94 yad tujhko yah Mera pyar aaega feel this video and follow me#sad #brakaupsong #brokenheart",
        "likes": "2196",
        "shares": "1774",
        "comments": "16"
      },
      {
        "url": "https://share.mxtakatak.com/eZR8Z6pk-x1J",
        "user": " Arishfa Khan\ud83e\udd81",
        "desc": "Tu batayega mujhe Ishq hai kya?\ud83c\udf39\ud83d\udd4a #arishfakhan #arishfashayari #shayari ",
        "likes": "10.1K",
        "shares": "221",
        "comments": "90"
      },
      {
        "url": "https://share.mxtakatak.com/6boyDGla-tsO",
        "user": " Garima Chaurasia  ",
        "desc": "Hayeee garmiiii \ud83d\udd25\ud83d\udc83\ud83c\udffc\u2665\ufe0f #garmi #hayegarmi #gimaashi ",
        "likes": "71.3K",
        "shares": "612",
        "comments": "190"
      },
      {
        "url": "https://share.mxtakatak.com/yrfBh6Nl-jmh",
        "user": " \ud83d\udca5RK RAJA \ud83d\udca5",
        "desc": "tera dil koi jab v dukhayega ",
        "likes": "539",
        "shares": "752",
        "comments": "6"
      },
      {
        "url": "https://share.mxtakatak.com/VZ230oqX-PW2",
        "user": " Rohit Zinjurke \ud83d\udcab",
        "desc": "Fir maar nai khayega tu \ud83d\ude21 #reactionboi #foryou",
        "likes": "5309",
        "shares": "68",
        "comments": "38"
      },
      {
        "url": "https://share.mxtakatak.com/chLezjKV-gvj",
        "user": " Mahi Khan  ",
        "desc": "Dil koi jab bhi dukhaega yaad tumhe saccha pyaar hi aayega \ud83d\udc94\ud83d\ude2d w/ #foryou",
        "likes": "4520",
        "shares": "88",
        "comments": "8"
      },
      {
        "url": "https://share.mxtakatak.com/o8zHEh5a-B2s",
        "user": " sanket singh",
        "desc": "Tera dil jab koi dukhayega yaad tujhko mera pyar aayega!!!!!\ud83e\udd17 #1millionaudition ",
        "likes": "694",
        "shares": "318",
        "comments": "27"
      },
      {
        "url": "https://share.mxtakatak.com/4Wkj5Y8N-F9g",
        "user": " Arishfa Khan\ud83e\udd81",
        "desc": "Woh aa kar bhi chala jayega.\u2764\ufe0f\u200d\ud83e\ude79 #arishfakhan #arishfashayari #shayari witharishfa ",
        "likes": "204",
        "shares": "27",
        "comments": "4"
      }
    ]
  },
  {
    "meri jaan": [
      {
        "url": "https://share.mxtakatak.com/TixukGrr-rhn",
        "user": " Yadit Acharya  ",
        "desc": "Meri jaan\u2764\ufe0f #yaditfam #yaditfamonmxtakatak",
        "likes": "7826",
        "shares": "70",
        "comments": "65"
      },
      {
        "url": "https://share.mxtakatak.com/2vhsarjk-p3Q",
        "user": " gulshankalra  ",
        "desc": "Meri jaan \u2764\ufe0f",
        "likes": "20.7K",
        "shares": "138",
        "comments": "24"
      },
      {
        "url": "https://share.mxtakatak.com/KfyyBqan-eCy",
        "user": " Ziddi_girl468",
        "desc": "good morning meri jaan\ud83d\ude18",
        "likes": "6943",
        "shares": "3307",
        "comments": "60"
      },
      {
        "url": "https://share.mxtakatak.com/pRmfh7cm-zbp",
        "user": " sachi sahu  ",
        "desc": "Meri jaan hai\ud83e\udd17\u2764\ufe0f\ud83e\udd17 #sachi",
        "likes": "21.3K",
        "shares": "2041",
        "comments": "44"
      },
      {
        "url": "https://share.mxtakatak.com/Wy3FQ6Sb-hp1",
        "user": " gulshankalra  ",
        "desc": "#meri jaan#gulshan #gulshankalra #takataktrending ",
        "likes": "19.5K",
        "shares": "105",
        "comments": "23"
      },
      {
        "url": "https://share.mxtakatak.com/mj13msqD-IUb",
        "user": " oye_indori  ",
        "desc": "Meri jaan \u2764\ufe0f\u2764\ufe0f",
        "likes": "99.7K",
        "shares": "655",
        "comments": "192"
      },
      {
        "url": "https://share.mxtakatak.com/Mr1ov1A1-F4d",
        "user": " Rugees Vini  ",
        "desc": "Chahe meri jaan jaaye\ud83d\udc94 #rugees",
        "likes": "23.1K",
        "shares": "90",
        "comments": "113"
      },
      {
        "url": "https://share.mxtakatak.com/zGqntxZl-G6q",
        "user": " Eshika Rao  ",
        "desc": "Tu meri jaan re\ud83d\ude41\u2764\ufe0f",
        "likes": "248.9K",
        "shares": "2025",
        "comments": "338"
      },
      {
        "url": "https://share.mxtakatak.com/AUuMWObQ-T69",
        "user": " Doll Daundkar  ",
        "desc": "Naach meri jaan \u2764\ufe0f #MxTakatak #TakatakCreator",
        "likes": "510.3K",
        "shares": "420",
        "comments": "2789"
      },
      {
        "url": "https://share.mxtakatak.com/Ulimm9MU-900",
        "user": " Shinchan\u2764\ufe0f  ",
        "desc": "Meri jaan mere dosto mein \u2665\ufe0f",
        "likes": "481.2K",
        "shares": "568",
        "comments": "803"
      },
      {
        "url": "https://share.mxtakatak.com/ilg27DC6-0zC",
        "user": " Zeba Qureshi 007",
        "desc": "i \u2764\ufe0f you meri Jaan \ud83d\ude18\ud83d\ude18\ud83d\ude18\ud83d\ude18\ud83d\ude18\ud83d\ude18",
        "likes": "1475",
        "shares": "2092",
        "comments": "29"
      },
      {
        "url": "https://share.mxtakatak.com/mQhM8dot-vk4",
        "user": " Isha Aashish Mittal  ",
        "desc": "Aap to meri jaan ho . \u2665\ufe0f\u2665\ufe0f\u2665\ufe0f #ishaash #jaan",
        "likes": "4144",
        "shares": "694",
        "comments": "10"
      },
      {
        "url": "https://share.mxtakatak.com/QT6wsTPm-k8H",
        "user": " khushi.punjaban  ",
        "desc": "Meri jaan ho tum \ud83d\ude0d\ud83e\udd70 #vkcouple04",
        "likes": "887.0K",
        "shares": "3008",
        "comments": "2881"
      },
      {
        "url": "https://share.mxtakatak.com/krLb8VC3-xcm",
        "user": " Rugees Vini  ",
        "desc": "Naach meri jaan \u2764\ufe0f #rugees #TakaTak",
        "likes": "300.3K",
        "shares": "215",
        "comments": "2135"
      },
      {
        "url": "https://share.mxtakatak.com/s2fFLhRg-WSy",
        "user": " Kanishka Talent hub  ",
        "desc": "Love you Meri Jaan \u2764\ufe0f@muskan_kalra01",
        "likes": "63.4K",
        "shares": "213",
        "comments": "110"
      },
      {
        "url": "https://share.mxtakatak.com/4woX9Ii8-sT4",
        "user": " my love Army  \ud83d\udc9e\ud83e\udd70",
        "desc": "me or meri jaan \ud83d\udc93\ud83d\udc9e",
        "likes": "397",
        "shares": "173",
        "comments": "1"
      },
      {
        "url": "https://share.mxtakatak.com/qNa02409-Eef",
        "user": " Ikra Ali509",
        "desc": "#hyy o meri jaan\u2764\ufe0f\u2764\ufe0f\u2764\ufe0f",
        "likes": "951",
        "shares": "501",
        "comments": "8"
      },
      {
        "url": "https://share.mxtakatak.com/uexbhDCt-95v",
        "user": " Deepak Joshi  ",
        "desc": "Oo meri jaan\u2764\ufe0f",
        "likes": "572.4K",
        "shares": "1064",
        "comments": "1940"
      },
      {
        "url": "https://share.mxtakatak.com/mF6bwIk5-Bu0",
        "user": " tu meri hai \ud83d\ude0b",
        "desc": "mere ammi meri jaan\ud83d\udc69\u200d\ud83d\udc67\ud83d\ude18",
        "likes": "508",
        "shares": "286",
        "comments": "5"
      },
      {
        "url": "https://share.mxtakatak.com/hWg22O2w-Og6",
        "user": " Lakhan Arjun Rawat  ",
        "desc": "Meri jaan",
        "likes": "19.3K",
        "shares": "575",
        "comments": "29"
      }
    ]
  }
]
